[{"city":"Kermanshah","cityF":"کرمانشاه","lat":"34.0283","lon":"46.2492"},
{"city":"Abad","cityF":"آباد","lat":"29.0283","lon":"51.2492"},
{"city":"Abadan","cityF":"آبادان","lat":"30.3392","lon":"48.3043"},
{"city":"Abadani","cityF":"آبادانی","lat":"27.2189","lon":"55.8053"},
{"city":"Abadeh","cityF":"آباده","lat":"29.1355","lon":"52.8571"},
{"city":"Abazar","cityF":"آباذر","lat":"38.0026","lon":"48.0706"},
{"city":"Abbas Abad","cityF":"عباس آباد","lat":"33.7939","lon":"47.6128"},
{"city":"Abbasabad","cityF":"عباس آباد","lat":"35.662","lon":"51.8867"},
{"city":"Abbasabad","cityF":"عباس آباد","lat":"36.1761","lon":"58.8925"},
{"city":"Abdanan","cityF":"آبدانان","lat":"32.9926","lon":"47.4198"},
{"city":"Abhar","cityF":"ابهر","lat":"36.1358","lon":"49.2203"},
{"city":"Abuzar","cityF":"ابوذر","lat":"33.3988","lon":"47.1894"},
{"city":"Abyek","cityF":"آبیک","lat":"36.0453","lon":"50.5233"},
{"city":"Adineh","cityF":"آدینه","lat":"33.8739","lon":"49.1281"},
{"city":"Afarin","cityF":"آفرین","lat":"36.5667","lon":"49.5"},
{"city":"Afra","cityF":"افرا","lat":"28.8836","lon":"52.8878"},
{"city":"Afra","cityF":"افرا","lat":"36.4333","lon":"52.8167"},
{"city":"Afraz","cityF":"افراز","lat":"28.9453","lon":"57.8978"},
{"city":"Afshan","cityF":"افشان","lat":"26.6511","lon":"61.6914"},
{"city":"Afshar","cityF":"افشار","lat":"35.8179","lon":"50.906"},
{"city":"Aftab","cityF":"آفتاب","lat":"34.2667","lon":"46.4"},
{"city":"Afzar","cityF":"افزار","lat":"31.4592","lon":"56.2697"},
{"city":"Agah","cityF":"آگاه","lat":"34.9125","lon":"47.3655"},
{"city":"Ahang","cityF":"آهنگ","lat":"34.3469","lon":"58.2686"},
{"city":"Ahang","cityF":"آهنگ","lat":"35.8603","lon":"52.5483"},
{"city":"Ahar","cityF":"اهر","lat":"38.4774","lon":"47.0699"},
{"city":"Ahel","cityF":"اهل","lat":"27.1675","lon":"53.7636"},
{"city":"Ahmadiyeh","cityF":"احمدیه","lat":"31.3678","lon":"49.4498"},
{"city":"Ahmadiyeh","cityF":"احمدیه","lat":"33.6994","lon":"56.8361"},
{"city":"Ahvaz","cityF":"اهواز","lat":"31.3203","lon":"48.6693"},
{"city":"Ahwaz","cityF":"اهواز","lat":"31.3553","lon":"48.7505"},
{"city":"Akram","cityF":"اکرم","lat":"34.8211","lon":"45.7228"},
{"city":"Alavi","cityF":"علوی","lat":"31.9333","lon":"48.45"},
{"city":"Alborz","cityF":"البرز","lat":"34","lon":"49.3833"},
{"city":"Alborz","cityF":"البرز","lat":"34.7282","lon":"50.9718"},
{"city":"Aleshtar","cityF":"الشتر","lat":"33.8644","lon":"48.2653"},
{"city":"Aliabad","cityF":"علی آباد","lat":"28.9658","lon":"53.1561"},
{"city":"Aligoodarz","cityF":"الیگودرز","lat":"33.3836","lon":"49.6964"},
{"city":"Almas","cityF":"الماس","lat":"37.5167","lon":"48.8333"},
{"city":"Almas","cityF":"الماس","lat":"38.3349","lon":"45.4323"},
{"city":"Almehdi","cityF":"المهدی","lat":"35.8346","lon":"50.9354"},
{"city":"Alvand","cityF":"الوند","lat":"36.3203","lon":"49.1733"},
{"city":"Amir","cityF":"امیر","lat":"26.8667","lon":"56.2"},
{"city":"Amir","cityF":"امیر","lat":"37.3019","lon":"46.2673"},
{"city":"Amol","cityF":"آمل","lat":"36.4708","lon":"52.3633"},
{"city":"Anar","cityF":"انار","lat":"38.482","lon":"47.8632"},
{"city":"Andimeshk","cityF":"اندیمشک","lat":"32.5333","lon":"48.3833"},
{"city":"Andisheh","cityF":"اندیشه","lat":"30.8203","lon":"50.8325"},
{"city":"Andisheh","cityF":"اندیشه","lat":"35.7004","lon":"50.9998"},
{"city":"Ansar","cityF":"انصار","lat":"35.4102","lon":"48.196"},
{"city":"Ansar","cityF":"انصار","lat":"37.5333","lon":"56.9"},
{"city":"Arad","cityF":"آراد","lat":"27.7289","lon":"53.6286"},
{"city":"Arad","cityF":"آراد","lat":"35.3425","lon":"51.3468"},
{"city":"Arak","cityF":"اراک","lat":"34.0856","lon":"49.6839"},
{"city":"Aras","cityF":"ارس","lat":"37.1344","lon":"47.7447"},
{"city":"Aras","cityF":"ارس","lat":"37.1455","lon":"47.7649"},
{"city":"Arash","cityF":"آرش","lat":"29.5136","lon":"50.6072"},
{"city":"Ardabil","cityF":"اردبیل","lat":"38.2498","lon":"48.2933"},
{"city":"Ardakan","cityF":"اردکان","lat":"32.3211","lon":"54.0208"},
{"city":"Ardebil","cityF":"اردبیل","lat":"38.2498","lon":"48.2933"},
{"city":"Ardejan","cityF":"اردجان","lat":"37.56","lon":"49.0894"},
{"city":"Ardestan","cityF":"اردستان","lat":"33.3725","lon":"52.375"},
{"city":"Arman","cityF":"آرمان","lat":"31.6353","lon":"50.7936"},
{"city":"Arsanjan","cityF":"ارسنجان","lat":"29.9142","lon":"53.3075"},
{"city":"Arsenjan","cityF":"ارسنجان","lat":"29.9142","lon":"53.3075"},
{"city":"Arvand","cityF":"اروند","lat":"36.3805","lon":"59.5815"},
{"city":"Aryan","cityF":"آریان","lat":"35.1455","lon":"46.5622"},
{"city":"Aryan","cityF":"آریان","lat":"35.7633","lon":"57.5325"},
{"city":"Asad Abad","cityF":"اسد آباد","lat":"32.9167","lon":"60.0283"},
{"city":"Asan","cityF":"آسان","lat":"37.5006","lon":"46.2969"},
{"city":"Asan","cityF":"آسان","lat":"37.5033","lon":"46.3042"},
{"city":"Ashena","cityF":"آشنا","lat":"36.45","lon":"49.9833"},
{"city":"Ashkanan","cityF":"اشکانان","lat":"32.7169","lon":"48.3122"},
{"city":"Ashtian","cityF":"آشتیان","lat":"34.525","lon":"50.0028"},
{"city":"Asrar","cityF":"اسرار","lat":"30.7892","lon":"61.4208"},
{"city":"Astan","cityF":"آستان","lat":"26.8944","lon":"58.0772"},
{"city":"Astana","cityF":"استانا","lat":"37.2333","lon":"48.95"},
{"city":"Astaneh","cityF":"آستانه","lat":"36.2708","lon":"54.0997"},
{"city":"Astara","cityF":"آستارا","lat":"38.4122","lon":"48.8761"},
{"city":"Avan","cityF":"آوان","lat":"36.4926","lon":"50.4514"},
{"city":"Avar","cityF":"اوار","lat":"35.4756","lon":"58.5861"},
{"city":"Avaran","cityF":"اواران","lat":"30.8139","lon":"56.0694"},
{"city":"Azad","cityF":"آزاد","lat":"36.5333","lon":"48.5167"},
{"city":"Azad","cityF":"آزاد","lat":"36.8122","lon":"45.9348"},
{"city":"Azad Shahr","cityF":"آزاد شهر","lat":"37.0858","lon":"55.1722"},
{"city":"Azadegan","cityF":"آزادان","lat":"27.2206","lon":"57.0567"},
{"city":"Azadegan","cityF":"آزادگان","lat":"30.5969","lon":"52.3447"},
{"city":"Azadi","cityF":"آزادی","lat":"32.0049","lon":"51.2222"},
{"city":"Azadi","cityF":"آزادی","lat":"33.5983","lon":"48.3244"},
{"city":"Azadshahr","cityF":"آزاد شهر","lat":"33.9356","lon":"49.4083"},
{"city":"Azali","cityF":"ازالی","lat":"27.91","lon":"57.7256"},
{"city":"Azar","cityF":"آذر","lat":"33.7122","lon":"51.1292"},
{"city":"Azar Shahr","cityF":"آذر شهر","lat":"37.759","lon":"45.9783"},
{"city":"Azna","cityF":"ازنا","lat":"33.6111","lon":"48.9314"},
{"city":"Baba","cityF":"بابا","lat":"30.7599","lon":"50.4829"},
{"city":"Baba","cityF":"بابا","lat":"36.6833","lon":"49.0833"},
{"city":"Babak","cityF":"بابک","lat":"39.4746","lon":"48.2346"},
{"city":"Babak","cityF":"بابک","lat":"39.4833","lon":"48.25"},
{"city":"Babel","cityF":"بابل","lat":"31.1736","lon":"49.6439"},
{"city":"Babol","cityF":"بابل","lat":"36.5442","lon":"52.6789"},
{"city":"Badr","cityF":"بدر","lat":"34.7336","lon":"46.6309"},
{"city":"Bafq","cityF":"بافق","lat":"31.6053","lon":"55.4028"},
{"city":"Baft","cityF":"بافت","lat":"29.2342","lon":"56.6069"},
{"city":"Bagh","cityF":"باغ","lat":"36.1672","lon":"45.5127"},
{"city":"Baghdad","cityF":"باغداد","lat":"33.7681","lon":"58.3158"},
{"city":"Baghestan","cityF":"باغستان","lat":"35.5667","lon":"56.7667"},
{"city":"Baghestan","cityF":"باغستان","lat":"36.3871","lon":"50.304"},
{"city":"Bahabad","cityF":"بهاباد","lat":"33.9833","lon":"54.4833"},
{"city":"Bahar","cityF":"بهار","lat":"34.9072","lon":"48.4414"},
{"city":"Baharan","cityF":"بهاران","lat":"33.917","lon":"47.2422"},
{"city":"Baharestan","cityF":"بهارستان","lat":"27.7006","lon":"52.7281"},
{"city":"Bahman","cityF":"بهمن","lat":"36.1263","lon":"48.255"},
{"city":"Bahmanshir","cityF":"بهمنشیر","lat":"30.4291","lon":"48.2219"},
{"city":"Bahreh","cityF":"بهره","lat":"36.6953","lon":"59.6033"},
{"city":"Bakhtiari","cityF":"بختیاری","lat":"28.0694","lon":"53.9806"},
{"city":"Bakhtiyari","cityF":"بختیاری","lat":"29.7503","lon":"54.1783"},
{"city":"Bala","cityF":"بالا","lat":"32.8167","lon":"59.1"},
{"city":"Bandar","cityF":"بندر","lat":"27.5444","lon":"56.3864"},
{"city":"Bandar","cityF":"بندر","lat":"36.4145","lon":"50.226"},
{"city":"Bane","cityF":"بانه","lat":"35.9975","lon":"45.8853"},
{"city":"Baneh","cityF":"بانه","lat":"35.9975","lon":"45.8853"},
{"city":"Bank","cityF":"بانک","lat":"27.871","lon":"52.0274"},
{"city":"Baran","cityF":"باران","lat":"39.3178","lon":"47.5193"},
{"city":"Barati","cityF":"براتی","lat":"32.8","lon":"52.4"},
{"city":"Bardeskan","cityF":"بدسکان","lat":"35.2664","lon":"57.9619"},
{"city":"Bardsir","cityF":"بردسیر","lat":"29.9264","lon":"56.575"},
{"city":"Barekat","cityF":"برکات","lat":"26.2075","lon":"60.3197"},
{"city":"Barekat","cityF":"برکات","lat":"28.589","lon":"51.3691"},
{"city":"Barg","cityF":"بارگ","lat":"32.0747","lon":"59.425"},
{"city":"Barid","cityF":"برید","lat":"28.1342","lon":"51.4284"},
{"city":"Bast","cityF":"بست","lat":"29.9203","lon":"50.4997"},
{"city":"Bastak","cityF":"بستک","lat":"35.9667","lon":"51.7833"},
{"city":"Bastam","cityF":"باستان","lat":"38.8851","lon":"44.9544"},
{"city":"Bavanat","cityF":"باونات","lat":"30.4667","lon":"53.45"},
{"city":"Bayan","cityF":"بایان","lat":"30.4531","lon":"53.17"},
{"city":"Bayer","cityF":"بایر","lat":"34.9466","lon":"46.1492"},
{"city":"Bazar","cityF":"بازار","lat":"37.5411","lon":"49.2117"},
{"city":"Bazargan","cityF":"بازرگان","lat":"36.4975","lon":"45.3869"},
{"city":"Behbahan","cityF":"بهبهان","lat":"30.5959","lon":"50.2417"},
{"city":"Behbehan","cityF":"بهبهان","lat":"30.5959","lon":"50.2417"},
{"city":"Behdasht","cityF":"بهدشت","lat":"33.6833","lon":"50.2"},
{"city":"Behshahr","cityF":"بهشهر","lat":"36.6944","lon":"53.5425"},
{"city":"Beshel","cityF":"بشل","lat":"36.35","lon":"52.8894"},
{"city":"Bidgol","cityF":"بیدگل","lat":"34.3092","lon":"46.6121"},
{"city":"Bijar","cityF":"بیجار","lat":"35.8727","lon":"47.6029"},
{"city":"Birjand","cityF":"بیرجند","lat":"32.8739","lon":"59.2144"},
{"city":"Boldaji","cityF":"بلداجی","lat":"31.9342","lon":"51.0578"},
{"city":"Boluk","cityF":"بلوک","lat":"36.9837","lon":"48.1818"},
{"city":"Bonab","cityF":"بناب","lat":"37.3292","lon":"46.0767"},
{"city":"Bonab","cityF":"بناب","lat":"38.4283","lon":"45.9071"},
{"city":"Bonyad","cityF":"بنیاد","lat":"28.3186","lon":"51.5447"},
{"city":"Bonyad","cityF":"بنیاد","lat":"35.8575","lon":"50.9421"},
{"city":"Borazjan","cityF":"برازجان","lat":"29.2666","lon":"51.2159"},
{"city":"Borujen","cityF":"بروجن","lat":"36.6958","lon":"53.5261"},
{"city":"Borujerd","cityF":"بروجرد","lat":"33.8667","lon":"48.8333"},
{"city":"Bostan","cityF":"بستان","lat":"31.7171","lon":"48.0005"},
{"city":"Bozorg","cityF":"بزرگ","lat":"26.1287","lon":"57.2283"},
{"city":"Bushehr","cityF":"بوشهر","lat":"28.9684","lon":"50.8385"},
{"city":"Chabahar","cityF":"چابهار","lat":"25.2919","lon":"60.643"},
{"city":"Chaboksar","cityF":"چابکسر","lat":"36.9592","lon":"50.5856"},
{"city":"Chadegan","cityF":"چادگان","lat":"32.77","lon":"50.6272"},
{"city":"Chahar Bagh","cityF":"چهار باغ","lat":"32.7667","lon":"51.6167"},
{"city":"Chahar Bagh","cityF":"چهار باغ","lat":"35.5894","lon":"50.7652"},
{"city":"Chahar Mahal","cityF":"چهار محل","lat":"29.6115","lon":"50.7584"},
{"city":"Chali","cityF":"چالی","lat":"35.5666","lon":"48.3245"},
{"city":"Chalus","cityF":"چالوس","lat":"36.6547","lon":"51.4219"},
{"city":"Chamestan","cityF":"چمستر","lat":"36.4633","lon":"52.2833"},
{"city":"Chamran","cityF":"چمران","lat":"35.1736","lon":"49.9272"},
{"city":"Chamran","cityF":"چمران","lat":"35.1789","lon":"49.928"},
{"city":"Chapar","cityF":"چاپار","lat":"36.0893","lon":"45.4306"},
{"city":"Chapar","cityF":"چاپار","lat":"37","lon":"47.6167"},
{"city":"Charook","cityF":"چاروک","lat":"30.4058","lon":"56.5064"},
{"city":"Chashm","cityF":"چشم","lat":"35.8919","lon":"53.2586"},
{"city":"Chasht","cityF":"چشت","lat":"29.7864","lon":"52.9822"},
{"city":"Chavil","cityF":"چویل","lat":"31.3044","lon":"50.2492"},
{"city":"Cheshmeh Pahn-e Nanaj","cityF":"چشمه پهن ناناج","lat":"34.4203","lon":"48.7519"},
{"city":"Chizar","cityF":"چیزار","lat":"35.7969","lon":"51.4531"},
{"city":"Dadeh","cityF":"داده","lat":"25.7333","lon":"59.3"},
{"city":"Daliran","cityF":"دلیران","lat":"32.7703","lon":"48.3856"},
{"city":"Daliran","cityF":"دلیران","lat":"36.45","lon":"52.25"},
{"city":"Damavand","cityF":"دماوند","lat":"35.7178","lon":"52.065"},
{"city":"Damghan","cityF":"دامغان","lat":"36.1667","lon":"54.3439"},
{"city":"Darab","cityF":"داراب","lat":"28.7519","lon":"54.5444"},
{"city":"Darabad","cityF":"دار آباد","lat":"35.8183","lon":"51.4914"},
{"city":"Daran","cityF":"داران","lat":"32.5422","lon":"51.8178"},
{"city":"Daran","cityF":"داران","lat":"38.8306","lon":"45.822"},
{"city":"Darband","cityF":"دربند","lat":"35.8134","lon":"51.4302"},
{"city":"Dargaz","cityF":"درگز","lat":"28.0397","lon":"56.7336"},
{"city":"Darmian","cityF":"دارمیان","lat":"32.8467","lon":"59.9492"},
{"city":"Daru","cityF":"دارو","lat":"27.3278","lon":"55.3786"},
{"city":"Dehghan","cityF":"دهقان","lat":"34.8167","lon":"49.9167"},
{"city":"Dehgolan","cityF":"دهگلان","lat":"35.278","lon":"47.4184"},
{"city":"Dehkadeh","cityF":"دهکده","lat":"29.7089","lon":"53.8711"},
{"city":"Dehkadeh","cityF":"دهکده","lat":"31.4644","lon":"48.4619"},
{"city":"Dehloran","cityF":"دهلران","lat":"32.6941","lon":"47.2679"},
{"city":"Delfan","cityF":"دلفان","lat":"33.5497","lon":"48.5278"},
{"city":"Delijan","cityF":"دلیجان","lat":"33.9903","lon":"50.6764"},
{"city":"Delvar","cityF":"دلور","lat":"28.7626","lon":"51.0697"},
{"city":"Deyhuk","cityF":"دیهوک","lat":"33.2958","lon":"57.5025"},
{"city":"Deylam","cityF":"دیلم","lat":"31.7769","lon":"48.867"},
{"city":"Dezfool","cityF":"دزفول","lat":"32.3825","lon":"48.402"},
{"city":"Dezful","cityF":"دزفول","lat":"32.3825","lon":"48.402"},
{"city":"Didgah","cityF":"دیدگاه","lat":"36.7","lon":"54.6"},
{"city":"Dizicheh","cityF":"دیزیچه","lat":"32.3844","lon":"51.5144"},
{"city":"Dorcheh","cityF":"درچه","lat":"32.6111","lon":"51.5561"},
{"city":"Dorud","cityF":"درود","lat":"36.9623","lon":"45.0198"},
{"city":"Ebrahimi","cityF":"ابراهیمی","lat":"27.5639","lon":"56.4667"},
{"city":"Emam","cityF":"امام","lat":"31.4645","lon":"49.4133"},
{"city":"Emam","cityF":"امام","lat":"36.6986","lon":"48.8136"},
{"city":"Emam Reza","cityF":"امام رضا","lat":"30.9466","lon":"49.7792"},
{"city":"Eram","cityF":"امام","lat":"36.4053","lon":"53.7017"},
{"city":"Eram","cityF":"امام","lat":"36.6","lon":"52.3333"},
{"city":"Esfahan","cityF":"اصفهان","lat":"32.6597","lon":"51.6714"},
{"city":"Esfarayen","cityF":"اسفراین","lat":"37.0733","lon":"57.5072"},
{"city":"Eshkanan","cityF":"اشکنان","lat":"27.2294","lon":"53.6083"},
{"city":"Eslamabad","cityF":"اسلام آباد","lat":"27.3836","lon":"57.1619"},
{"city":"Eslamshahr","cityF":"اسلامشهر","lat":"35.5605","lon":"51.2346"},
{"city":"Estahban","cityF":"استهبان","lat":"29.1253","lon":"54.0397"},
{"city":"Evaz","cityF":"اواز","lat":"27.7633","lon":"54.0103"},
{"city":"Evin","cityF":"اوین","lat":"35.7939","lon":"51.3935"},
{"city":"Evin","cityF":"اوین","lat":"38.9931","lon":"47.3581"},
{"city":"Eyvanaki","cityF":"ایوانکی","lat":"35.3453","lon":"52.0631"},
{"city":"Eziran","cityF":"ازیران","lat":"32.4956","lon":"51.9097"},
{"city":"Falak","cityF":"فلک","lat":"33.7194","lon":"58.955"},
{"city":"Falavarjan","cityF":"فلاورجان","lat":"32.5564","lon":"51.51"},
{"city":"Famenin","cityF":"فامنین","lat":"35.0922","lon":"48.9769"},
{"city":"Faran","cityF":"فاران","lat":"32.9894","lon":"52.6242"},
{"city":"Fardis","cityF":"فردیس","lat":"35.4453","lon":"51.5953"},
{"city":"Farhangian","cityF":"فرهنگیان","lat":"37.4833","lon":"45.8667"},
{"city":"Farhangian","cityF":"فرهنگیان","lat":"37.4972","lon":"45.8789"},
{"city":"Farid","cityF":"فرید","lat":"32.4172","lon":"47.5111"},
{"city":"Farmahin","cityF":"فرمهین","lat":"34.5044","lon":"49.6803"},
{"city":"Farrokh","cityF":"فرخ","lat":"32.1333","lon":"48.4667"},
{"city":"Farrokhshahr","cityF":"فرخ شهر","lat":"32.2728","lon":"50.9822"},
{"city":"Fars","cityF":"فرس","lat":"35.1825","lon":"59.3881"},
{"city":"Farsan","cityF":"فرسان","lat":"32.2569","lon":"50.5642"},
{"city":"Farsi","cityF":"فرسی","lat":"27.2803","lon":"52.8289"},
{"city":"Faruj","cityF":"فروج","lat":"37.2328","lon":"58.2183"},
{"city":"Fasa","cityF":"فسا","lat":"28.9383","lon":"53.6482"},
{"city":"Fasham","cityF":"فشم","lat":"35.9306","lon":"51.5266"},
{"city":"Fasham","cityF":"فشم","lat":"37.2814","lon":"49.8731"},
{"city":"Fassa","cityF":"فسا","lat":"28.9394","lon":"53.65"},
{"city":"Fatemiyeh","cityF":"فاطمیه","lat":"33.558","lon":"46.7918"},
{"city":"Ferdows","cityF":"فردوس","lat":"35.7489","lon":"50.8895"},
{"city":"Ferdows","cityF":"فردوس","lat":"36.5833","lon":"49.2333"},
{"city":"Ferdowsi","cityF":"فردوسی","lat":"37.4","lon":"57.8333"},
{"city":"Firozabad","cityF":"فیروآباد","lat":"33.1","lon":"46.1167"},
{"city":"Fisherabad","cityF":"فیشرآباد","lat":"35.6667","lon":"51.4333"},
{"city":"Gachsaran","cityF":"گچساران","lat":"30.3586","lon":"50.7981"},
{"city":"Ganaveh","cityF":"گناوه","lat":"28.05","lon":"51.9167"},
{"city":"Ganaveh","cityF":"گناوه","lat":"30.4539","lon":"50.8361"},
{"city":"Garmeh","cityF":"گرمه","lat":"30.5142","lon":"52.0814"},
{"city":"Garmeh","cityF":"گرمه","lat":"33.8207","lon":"46.5"},
{"city":"Garmsar","cityF":"گرمسار","lat":"35.2222","lon":"52.3406"},
{"city":"Gasht","cityF":"گشت","lat":"37.1708","lon":"49.2653"},
{"city":"Gazi","cityF":"گازی","lat":"26.072","lon":"57.233"},
{"city":"Genaveh","cityF":"گناوه","lat":"29.5791","lon":"50.517"},
{"city":"Gerash","cityF":"گراش","lat":"27.6697","lon":"54.1383"},
{"city":"Germi","cityF":"گرمی","lat":"39.0215","lon":"48.0801"},
{"city":"Ghadir","cityF":"قدیر","lat":"26.8778","lon":"53.9669"},
{"city":"Gharbi","cityF":"غربی","lat":"28.9361","lon":"53.2483"},
{"city":"Ghasr","cityF":"قصر","lat":"28.9306","lon":"58.6842"},
{"city":"Ghasre Shirin","cityF":"قصر شیرین","lat":"34.514814","lon":"45.57732"},
{"city":"Ghazanfari","cityF":"غضنفر","lat":"30.3167","lon":"51.1"},
{"city":"Ghaznavi","cityF":"غضنوی","lat":"36.9331","lon":"55.4656"},
{"city":"Ghazvin","cityF":"","lat":"35.6069","lon":"47.0341"},
{"city":"Ghom","cityF":"قم","lat":"34.6401","lon":"50.8764"},
{"city":"Ghom","cityF":"قم","lat":"34.6453","lon":"50.8808"},
{"city":"Ghorveh","cityF":"غروه","lat":"36.0533","lon":"49.3872"},
{"city":"Gilan","cityF":"گیلان","lat":"34.1421","lon":"45.9203"},
{"city":"Gilan","cityF":"گیلان","lat":"36.5958","lon":"55.5419"},
{"city":"Gilas","cityF":"گیلاس","lat":"35.8833","lon":"52.2"},
{"city":"Gohar","cityF":"گهر","lat":"32.1667","lon":"49.3"},
{"city":"Golestan","cityF":"گلستان","lat":"27.4494","lon":"57.2181"},
{"city":"Golestan","cityF":"گلستان","lat":"35.7757","lon":"51.4721"},
{"city":"Golpayegan","cityF":"گلپایگان","lat":"33.4533","lon":"50.2872"},
{"city":"Golshahr","cityF":"گلشهر","lat":"36.3131","lon":"59.7453"},
{"city":"Golshahr","cityF":"گلشهر","lat":"38.0348","lon":"46.3697"},
{"city":"Gonabad","cityF":"گناباد","lat":"34.3389","lon":"58.7008"},
{"city":"Gonar","cityF":"گنار","lat":"26.8652","lon":"57.4494"},
{"city":"Gonar","cityF":"گنار","lat":"36.55","lon":"51"},
{"city":"Gonbad","cityF":"گنبد","lat":"36.1508","lon":"48.0439"},
{"city":"Gonbad","cityF":"گنبد","lat":"37.5021","lon":"46.0393"},
{"city":"Gorgan","cityF":"گرگان","lat":"36.8394","lon":"54.4361"},
{"city":"Gostar","cityF":"گستر","lat":"35.4667","lon":"48.8833"},
{"city":"Gotvand","cityF":"گتوند","lat":"32.2453","lon":"48.8138"},
{"city":"Hadi","cityF":"هادی","lat":"30.6725","lon":"51.9608"},
{"city":"Hadishahr","cityF":"هادیشهر","lat":"38.8479","lon":"45.6623"},
{"city":"Hafez","cityF":"حافظ","lat":"37.5723","lon":"47.2242"},
{"city":"Hafshejan","cityF":"هفشه جان","lat":"32.2217","lon":"50.795"},
{"city":"Hajiabad","cityF":"حاجی آباد","lat":"32.6521","lon":"51.2498"},
{"city":"Hakim","cityF":"حکیم","lat":"31.1711","lon":"53.3767"},
{"city":"Hamadan","cityF":"همدان","lat":"34.7961","lon":"48.5158"},
{"city":"Hamedan","cityF":"همدان","lat":"30.4933","lon":"54.2558"},
{"city":"Hamgam","cityF":"همگام","lat":"32.95","lon":"47.7833"},
{"city":"Hamid","cityF":"حمید","lat":"30.0949","lon":"48.4414"},
{"city":"Hamid","cityF":"حمید","lat":"36.5803","lon":"45.6575"},
{"city":"Hamidiyeh","cityF":"حمیدیه","lat":"31.485","lon":"48.4353"},
{"city":"Hasan","cityF":"حسن","lat":"33.5748","lon":"46.6876"},
{"city":"Hasanak","cityF":"حسنک","lat":"35.4092","lon":"60.1658"},
{"city":"Hash","cityF":"هش","lat":"34.9061","lon":"46.1592"},
{"city":"Hashtgerd","cityF":"هشتگرد","lat":"35.962","lon":"50.6799"},
{"city":"Hazrati","cityF":"حضرتی","lat":"33.95","lon":"59.2667"},
{"city":"Hedayat","cityF":"هدایت","lat":"34.5821","lon":"45.5523"},
{"city":"Hejrat","cityF":"حجرت","lat":"30.6333","lon":"50.75"},
{"city":"Hejrat","cityF":"حجرت","lat":"35.4729","lon":"46.195"},
{"city":"Helal","cityF":"حلال","lat":"36.715","lon":"59.0797"},
{"city":"Hemayat","cityF":"حمایت","lat":"30.7983","lon":"49.2837"},
{"city":"Hesar","cityF":"حصار","lat":"36.3061","lon":"59.4039"},
{"city":"Hezar","cityF":"هزار","lat":"29.8865","lon":"52.5188"},
{"city":"Hezareh","cityF":"هزاره","lat":"34.4833","lon":"48.25"},
{"city":"Homa","cityF":"هما","lat":"33.0906","lon":"49.7847"},
{"city":"Hoor","cityF":"هور","lat":"26.9964","lon":"58.6356"},
{"city":"Hormoz","cityF":"هرمز","lat":"27.5022","lon":"54.2853"},
{"city":"Hormozan","cityF":"هرمزگان","lat":"31.7667","lon":"55.8667"},
{"city":"Human","cityF":"هومن","lat":"32.7833","lon":"51"},
{"city":"Ideh","cityF":"ایده","lat":"37.6833","lon":"57.4833"},
{"city":"Ilam","cityF":"ایلام","lat":"33.6374","lon":"46.4227"},
{"city":"Ilika","cityF":"ایلیکا","lat":"36.2106","lon":"51.4072"},
{"city":"Ilkhchi","cityF":"ایلچی","lat":"37.9373","lon":"45.979"},
{"city":"Imam","cityF":"ایمان","lat":"36.6986","lon":"48.8136"},
{"city":"Imam Khomeyni","cityF":"امام خمینی","lat":"30.4356","lon":"49.1056"},
{"city":"Iman","cityF":"ایمان","lat":"38.4618","lon":"47.2757"},
{"city":"Iran","cityF":"ایران","lat":"32.0913","lon":"51.0292"},
{"city":"Irancheh","cityF":"ایرانچه","lat":"32.0913","lon":"51.0292"},
{"city":"Iranshahr","cityF":"ایرانشهر","lat":"27.2039","lon":"60.6919"},
{"city":"Isfahan","cityF":"اصفهان","lat":"32.6597","lon":"51.6714"},
{"city":"Izeh","cityF":"ایذه","lat":"31.8372","lon":"49.8694"},
{"city":"Jadid","cityF":"جدید","lat":"28.5592","lon":"53.5552"},
{"city":"Jahad","cityF":"جهان","lat":"31.298","lon":"48.5852"},
{"city":"Jahan","cityF":"جهان","lat":"36.9447","lon":"57.8553"},
{"city":"Jahrom","cityF":"جهرم","lat":"28.4942","lon":"53.5583"},
{"city":"Jajarm","cityF":"ججارم","lat":"36.9547","lon":"56.3733"},
{"city":"Jalal","cityF":"جلال","lat":"33.9017","lon":"47.1299"},
{"city":"Jamshid","cityF":"جمشید","lat":"28.7061","lon":"54.4742"},
{"city":"Janbazan","cityF":"جانبازان","lat":"35.7972","lon":"50.9467"},
{"city":"Jannat","cityF":"جنت","lat":"29.6078","lon":"52.4713"},
{"city":"Jannat","cityF":"جنت","lat":"31.6167","lon":"56.1833"},
{"city":"Jask","cityF":"جاسک","lat":"25.6422","lon":"57.7722"},
{"city":"Javadi","cityF":"جوادی","lat":"33.9","lon":"51.85"},
{"city":"Javanan","cityF":"جوانان","lat":"28.7794","lon":"54.3714"},
{"city":"Jiroft","cityF":"جیرفت","lat":"28.6703","lon":"57.7369"},
{"city":"Jolfa","cityF":"جلفا","lat":"32.6333","lon":"51.6167"},
{"city":"Jolfa","cityF":"جلفا","lat":"38.9404","lon":"45.6308"},
{"city":"Jomhuri","cityF":"جمهوری","lat":"36.1742","lon":"58.6383"},
{"city":"Jooneghan","cityF":"جونقان","lat":"32.1522","lon":"50.6911"},
{"city":"Kabir","cityF":"کبیر","lat":"36.6667","lon":"59.1494"},
{"city":"Kahnooj","cityF":"کهنوج","lat":"29.2808","lon":"56.9953"},
{"city":"Kala","cityF":"","lat":"36.16","lon":"51.9422"},
{"city":"Kalaleh","cityF":"کلاله","lat":"37.3706","lon":"55.4994"},
{"city":"Kalat","cityF":"","lat":"27.3189","lon":"56.0965"},
{"city":"Kalat","cityF":"کلات","lat":"36.2422","lon":"49.5553"},
{"city":"Kaleh","cityF":"کله","lat":"37.7365","lon":"46.7818"},
{"city":"Kalleh Bast","cityF":"کله","lat":"36.6406","lon":"52.6297"},
{"city":"Kamal","cityF":"کمال","lat":"35.8521","lon":"50.6107"},
{"city":"Kamalvand","cityF":"کمالوند","lat":"33.4608","lon":"48.4208"},
{"city":"Kaman","cityF":"کمال","lat":"36.4639","lon":"50.138"},
{"city":"Kamyaran","cityF":"کامیاران","lat":"34.7956","lon":"46.9355"},
{"city":"Kangan","cityF":"کنگان","lat":"27.834","lon":"52.0628"},
{"city":"Kangavar","cityF":"کنگاور","lat":"34.5043","lon":"47.9653"},
{"city":"Karadj","cityF":"کارادج","lat":"35.8355","lon":"51.0103"},
{"city":"Karadje","cityF":"کارادج","lat":"35.8355","lon":"51.0103"},
{"city":"Karag","cityF":"کاراگ","lat":"30.0667","lon":"55.8333"},
{"city":"Karaj","cityF":"کرج","lat":"35.8355","lon":"51.0103"},
{"city":"Karbala","cityF":"کربلا","lat":"25.7167","lon":"58.85"},
{"city":"Karbala","cityF":"کربلا","lat":"36.4177","lon":"48.0128"},
{"city":"Karimkhan","cityF":"کریمخان","lat":"36.5792","lon":"59.2947"},
{"city":"Kariz","cityF":"کریز","lat":"35.6877","lon":"47.8894"},
{"city":"Kashan","cityF":"کاشان","lat":"29.6257","lon":"52.4657"},
{"city":"Kashanak","cityF":"کاشانک","lat":"33.1728","lon":"52.6053"},
{"city":"Kashani","cityF":"کاشانی","lat":"35.9833","lon":"50.5"},
{"city":"Kashmar","cityF":"کاشمر","lat":"35.2364","lon":"58.4819"},
{"city":"Kavan","cityF":"کاوان","lat":"37.3922","lon":"48.1989"},
{"city":"Kavan","cityF":"کاوان","lat":"37.3933","lon":"48.2006"},
{"city":"Kavar","cityF":"کور","lat":"29.1974","lon":"52.7218"},
{"city":"Kaveh","cityF":"کاوه","lat":"34.1295","lon":"47.6593"},
{"city":"Kavir","cityF":"کویر","lat":"38.9707","lon":"47.4527"},
{"city":"Kazemi","cityF":"کاظمی","lat":"30.9828","lon":"48.368"},
{"city":"Kelarabad","cityF":"کلار آباد","lat":"36.6781","lon":"51.3103"},
{"city":"Kelishad","cityF":"کلیشاد","lat":"32.5411","lon":"51.5314"},
{"city":"Kerman","cityF":"کرمان","lat":"30.2939","lon":"57.0842"},
{"city":"Kermani","cityF":"کرمانی","lat":"31.4833","lon":"55.9833"},
{"city":"Kermanshah","cityF":"کرمانشاه","lat":"34.3142","lon":"47.065"},
{"city":"Keshavarzi","cityF":"کشاورزی","lat":"29.3868","lon":"52.0136"},
{"city":"Keshvar","cityF":"کشور","lat":"33.1378","lon":"48.6408"},
{"city":"Keyhan","cityF":"کیهان","lat":"36.75","lon":"49.7"},
{"city":"Khabar","cityF":"خبر","lat":"28.8194","lon":"56.3319"},
{"city":"Khaf","cityF":"خاف","lat":"34.5664","lon":"60.1431"},
{"city":"Khajeh","cityF":"خاجه","lat":"38.1508","lon":"46.5815"},
{"city":"Khalil","cityF":"خلیل","lat":"30.3833","lon":"51.4"},
{"city":"Khalkhal","cityF":"خلخال","lat":"37.6117","lon":"48.5258"},
{"city":"Khamir","cityF":"خمیر","lat":"26.9521","lon":"55.5851"},
{"city":"Khan","cityF":"خان","lat":"38.8943","lon":"44.2887"},
{"city":"Khaneh","cityF":"خانه","lat":"36.701","lon":"45.1413"},
{"city":"Khansar","cityF":"خانسار","lat":"33.2194","lon":"50.3114"},
{"city":"Khark","cityF":"خارک","lat":"29.2614","lon":"50.3306"},
{"city":"Khash","cityF":"خاش","lat":"28.2197","lon":"61.2131"},
{"city":"Khashmar","cityF":"خاشمر","lat":"35.2364","lon":"58.4819"},
{"city":"Khayyam","cityF":"خیام","lat":"29.0333","lon":"52.95"},
{"city":"Khayyam","cityF":"خیام","lat":"34.3068","lon":"47.0526"},
{"city":"Khesht","cityF":"خشت","lat":"27.2422","lon":"53.4464"},
{"city":"Khezri","cityF":"","lat":"28.9224","lon":"51.2726"},
{"city":"Khodabandeh","cityF":"خدابنده","lat":"35.2481","lon":"59.2678"},
{"city":"Khomam","cityF":"خمام","lat":"37.0244","lon":"48.9667"},
{"city":"Khomein","cityF":"خمین","lat":"33.6436","lon":"50.0781"},
{"city":"Khomeynishahr","cityF":"خمینی شهر","lat":"32.6861","lon":"51.5319"},
{"city":"Khoram","cityF":"خرم","lat":"34.6333","lon":"46.5833"},
{"city":"Khorasan","cityF":"خراسان","lat":"35.7131","lon":"47.2656"},
{"city":"Khorasgan","cityF":"خراسگان","lat":"32.6528","lon":"51.7514"},
{"city":"Khorramabad","cityF":"خرم آباد","lat":"33.4878","lon":"48.3558"},
{"city":"Khorramshahr","cityF":"خرم شهر","lat":"30.4397","lon":"48.1664"},
{"city":"Khorshid","cityF":"خورشید","lat":"36.7464","lon":"53.2803"},
{"city":"Khorshidi","cityF":"خورشیدی","lat":"28.9484","lon":"51.046"},
{"city":"Khoy","cityF":"خوی","lat":"38.5503","lon":"44.9521"},
{"city":"Khosrai","cityF":"خسروی","lat":"34.38921","lon":"45.47130"},
{"city":"Khoy","cityF":"خوی","lat":"38.5525","lon":"44.9478"},
{"city":"Kian","cityF":"کیان","lat":"36.05","lon":"52.2167"},
{"city":"Kish","cityF":"کیش","lat":"26.5578","lon":"54.0194"},
{"city":"Komijan","cityF":"کمیجان","lat":"34.7203","lon":"49.3278"},
{"city":"Kordabad","cityF":"کرد آباد","lat":"35.663","lon":"50.9789"},
{"city":"Kordestan","cityF":"کردستان","lat":"30.6693","lon":"50.2055"},
{"city":"Kowsar","cityF":"کوثر","lat":"31.0333","lon":"56.55"},
{"city":"Kowsar","cityF":"کوثر","lat":"31.9834","lon":"49.4052"},
{"city":"Kurd","cityF":"کرد","lat":"32.8975","lon":"50.7856"},
{"city":"Kurdistan","cityF":"کردستان","lat":"30.6693","lon":"50.2055"},
{"city":"Lahijan","cityF":"لاهیجان","lat":"37.2092","lon":"50.0006"},
{"city":"Lalejin","cityF":"لالجین","lat":"34.9731","lon":"48.4781"},
{"city":"Lamerd","cityF":"لامرد","lat":"27.3347","lon":"53.1797"},
{"city":"Langrood","cityF":"لنگرود","lat":"34.13","lon":"49.1886"},
{"city":"Larestan","cityF":"لارستان","lat":"35.7167","lon":"54.0833"},
{"city":"Lashtenesha","cityF":"لاشتنشا","lat":"37.3644","lon":"49.8578"},
{"city":"Lavasan","cityF":"لواسان","lat":"35.825","lon":"51.7828"},
{"city":"Lavasan","cityF":"لواسان","lat":"38.0449","lon":"46.2022"},
{"city":"Lengeh","cityF":"لنگه","lat":"26.5561","lon":"54.8808"},
{"city":"Lenjan","cityF":"لنجان","lat":"30.6631","lon":"56.9058"},
{"city":"Lordegan","cityF":"لردگان","lat":"31.5097","lon":"50.8283"},
{"city":"Mahabad","cityF":"مهاباد","lat":"36.7499","lon":"45.7229"},
{"city":"Mahallat","cityF":"محلات","lat":"33.9033","lon":"50.4667"},
{"city":"Mahan","cityF":"ماهان","lat":"30.0608","lon":"57.2914"},
{"city":"Mahdavi","cityF":"مهدوی","lat":"36.5978","lon":"57.9997"},
{"city":"Mahdieh","cityF":"محدیه","lat":"29.7066","lon":"52.4806"},
{"city":"Mahestan","cityF":"ماهستان","lat":"33.7","lon":"50.3333"},
{"city":"Mahshahr","cityF":"ماهشهر","lat":"30.5588","lon":"49.1981"},
{"city":"Mahtab","cityF":"مهتاب","lat":"31.2","lon":"50.6489"},
{"city":"Majid","cityF":"مجید","lat":"31.9588","lon":"48.5914"},
{"city":"Majid","cityF":"مجید","lat":"36.1675","lon":"53.2331"},
{"city":"Majin","cityF":"مجین","lat":"35.1737","lon":"47.9471"},
{"city":"Maku","cityF":"ماکو","lat":"39.2944","lon":"44.4809"},
{"city":"Malayer","cityF":"ملایر","lat":"34.2942","lon":"48.82"},
{"city":"Malek","cityF":"ملک","lat":"38.7103","lon":"46.5449"},
{"city":"Malekan","cityF":"ملکان","lat":"37.1375","lon":"46.1103"},
{"city":"Malekan","cityF":"ملکان","lat":"37.1458","lon":"46.1027"},
{"city":"Mamagan","cityF":"ماماگان","lat":"37.843","lon":"45.9757"},
{"city":"Mamasani","cityF":"ممسنی","lat":"31.45","lon":"50.4833"},
{"city":"Manjil","cityF":"منجیل","lat":"36.7328","lon":"49.4203"},
{"city":"Mansoori","cityF":"منصوری","lat":"31.1062","lon":"61.398"},
{"city":"Mansoori","cityF":"منصوری","lat":"32.0553","lon":"54.7303"},
{"city":"Maragheh","cityF":"مراغه","lat":"37.3817","lon":"46.2544"},
{"city":"Maragheh","cityF":"مراغه","lat":"37.3893","lon":"46.2376"},
{"city":"Marand","cityF":"مرند","lat":"38.4281","lon":"45.7753"},
{"city":"Marand","cityF":"مرند","lat":"38.4329","lon":"45.7749"},
{"city":"Marivan","cityF":"مریوان","lat":"35.527","lon":"46.1763"},
{"city":"Marvast","cityF":"مرواست","lat":"30.4783","lon":"54.2117"},
{"city":"Masal","cityF":"ماسال","lat":"37.3911","lon":"49.1333"},
{"city":"Mashad","cityF":"مشد","lat":"36.297","lon":"59.6062"},
{"city":"Mashhad","cityF":"مشهد","lat":"36.297","lon":"59.6062"},
{"city":"Mashin","cityF":"ماشین","lat":"28.42","lon":"60.8828"},
{"city":"Mashiz","cityF":"ماشیز","lat":"29.9264","lon":"56.575"},
{"city":"Masina","cityF":"مسینا","lat":"32.8067","lon":"60.2331"},
{"city":"Masiri","cityF":"مسیری","lat":"30.8387","lon":"50.1831"},
{"city":"Masjed","cityF":"مسجد","lat":"29.6555","lon":"52.4791"},
{"city":"Maskan","cityF":"مسکن","lat":"36.1647","lon":"57.4836"},
{"city":"Mehdi","cityF":"مهدی","lat":"31.7333","lon":"55.95"},
{"city":"Mehdi","cityF":"مهدی","lat":"31.8303","lon":"48.851"},
{"city":"Mehr","cityF":"مهر","lat":"27.5556","lon":"52.8858"},
{"city":"Mehr","cityF":"مهر","lat":"33.437","lon":"46.461"},
{"city":"Mehrabad","cityF":"مهر آباد","lat":"36.8951","lon":"47.9286"},
{"city":"Mehraban","cityF":"مهرابان","lat":"38.0798","lon":"47.1314"},
{"city":"Mehran","cityF":"مهران","lat":"33.1222","lon":"46.1646"},
{"city":"Mehregan","cityF":"مهرگان","lat":"34.6984","lon":"46.7183"},
{"city":"Mehriz","cityF":"مهریز","lat":"31.5839","lon":"54.4281"},
{"city":"Melli","cityF":"ملی","lat":"36.7347","lon":"59.0511"},
{"city":"Meshgin Shahr","cityF":"مشگین شهر","lat":"38.399","lon":"47.682"},
{"city":"Meshkin Shahr","cityF":"مشکین شهر","lat":"38.399","lon":"47.682"},
{"city":"Meybod","cityF":"میبد","lat":"32.2314","lon":"54.0133"},
{"city":"Meydan","cityF":"میدان","lat":"36.38","lon":"50.595"},
{"city":"Meydan","cityF":"میدان","lat":"39.1198","lon":"44.4261"},
{"city":"Miandoab","cityF":"میاندواب","lat":"36.9694","lon":"46.1027"},
{"city":"Mianeh","cityF":"میانه","lat":"37.4133","lon":"47.7242"},
{"city":"Mianeh","cityF":"میانه","lat":"37.421","lon":"47.715"},
{"city":"Mihan","cityF":"میهن","lat":"36.1211","lon":"49.4831"},
{"city":"Minab","cityF":"میناب","lat":"27.1467","lon":"57.0801"},
{"city":"Miyandoab","cityF":"میاندواب","lat":"36.9611","lon":"46.1092"},
{"city":"Miyandoab","cityF":"میاندواب","lat":"36.9694","lon":"46.1027"},
{"city":"Miyaneh","cityF":"میانه","lat":"37.421","lon":"47.715"},
{"city":"Mobarakeh","cityF":"مبارکه","lat":"29.9827","lon":"52.3807"},
{"city":"Moghan","cityF":"مغان","lat":"36.1368","lon":"59.3794"},
{"city":"Moghan","cityF":"مغان","lat":"36.3758","lon":"54.9586"},
{"city":"Mohajeran","cityF":"مهاجران","lat":"35.0622","lon":"48.6242"},
{"city":"Mohammad","cityF":"مجمد","lat":"30.4169","lon":"50.5369"},
{"city":"Mohammadiyeh","cityF":"محمدیه","lat":"32.3071","lon":"51.4371"},
{"city":"Mohr","cityF":"مهر","lat":"27.5556","lon":"52.8858"},
{"city":"Mohsen","cityF":"محسن","lat":"31.1179","lon":"49.38"},
{"city":"Mojen","cityF":"موجن","lat":"36.4878","lon":"54.645"},
{"city":"Molla","cityF":"ملا","lat":"28.4333","lon":"55.7167"},
{"city":"Mortazavi","cityF":"مرتضوی","lat":"35.1942","lon":"59.1372"},
{"city":"Morteza","cityF":"مرتضی","lat":"32.1557","lon":"48.8849"},
{"city":"Morteza","cityF":"مرتضی","lat":"33.8833","lon":"58.8333"},
{"city":"Mostafa","cityF":"مصطفی","lat":"34.3833","lon":"45.9"},
{"city":"Mozaffar","cityF":"مظفر","lat":"35.5439","lon":"51.2534"},
{"city":"Naderi","cityF":"نادری","lat":"35.7635","lon":"47.5297"},
{"city":"Naghadeh","cityF":"نقده","lat":"36.9553","lon":"45.388"},
{"city":"Naghadeh","cityF":"نقده","lat":"36.9564","lon":"45.3881"},
{"city":"Nahar","cityF":"نهار","lat":"35.9333","lon":"52.3"},
{"city":"Nahar","cityF":"نهار","lat":"38.5509","lon":"46.8566"},
{"city":"Nahavand","cityF":"نهاوند","lat":"34.1919","lon":"48.3658"},
{"city":"Najaf","cityF":"نجف","lat":"37.5961","lon":"56.8564"},
{"city":"Najaf","cityF":"نجف","lat":"39.0815","lon":"47.396"},
{"city":"Najafabad","cityF":"نجف آباد","lat":"32.6344","lon":"51.3668"},
{"city":"Najafi","cityF":"نجفی","lat":"33.8333","lon":"48.25"},
{"city":"Namin","cityF":"نمین","lat":"38.4269","lon":"48.4839"},
{"city":"Naqadeh","cityF":"نقده","lat":"36.9553","lon":"45.388"},
{"city":"Nargan","cityF":"نارگان","lat":"32.4667","lon":"51.5167"},
{"city":"Narmak","cityF":"نارمک","lat":"35.7558","lon":"51.5157"},
{"city":"Naser","cityF":"ناصر","lat":"33.3167","lon":"60.1333"},
{"city":"Natanz","cityF":"نطنز","lat":"33.5297","lon":"51.9039"},
{"city":"Nazar","cityF":"نظر","lat":"30.6842","lon":"49.3262"},
{"city":"Nazar","cityF":"نظر","lat":"34.3108","lon":"50.5322"},
{"city":"Negar","cityF":"نگار","lat":"25.8469","lon":"57.6264"},
{"city":"Negareh","cityF":"نگاره","lat":"34.8971","lon":"46.0141"},
{"city":"Negarestan","cityF":"نگارستان","lat":"29.9912","lon":"52.5135"},
{"city":"Nehbandan","cityF":"نهبندان","lat":"31.5361","lon":"60.0356"},
{"city":"Neka","cityF":"نکا","lat":"36.6514","lon":"53.2969"},
{"city":"Neyriz","cityF":"نی ریز","lat":"29.1986","lon":"54.3264"},
{"city":"Neyshabur","cityF":"نیشابور","lat":"36.2097","lon":"58.7989"},
{"city":"Niasar","cityF":"نیاصر","lat":"33.9731","lon":"51.1464"},
{"city":"Nimruz","cityF":"نیمروز","lat":"33.95","lon":"59.2667"},
{"city":"Nimvar","cityF":"نیم ور","lat":"33.8847","lon":"50.5717"},
{"city":"Novin","cityF":"نوین","lat":"35.1899","lon":"46.3587"},
{"city":"Nowin","cityF":"نوین","lat":"35.1899","lon":"46.3587"},
{"city":"Nowshahr","cityF":"نوشهر","lat":"37.7","lon":"46.8167"},
{"city":"Nowshahr","cityF":"نوشهر","lat":"37.7035","lon":"46.8189"},
{"city":"Omidiyeh","cityF":"امیدیه","lat":"30.7458","lon":"49.7087"},
{"city":"Orumiyeh","cityF":"ارومیه","lat":"37.555","lon":"45.1028"},
{"city":"Orumiyeh","cityF":"ارومیه","lat":"37.5553","lon":"45.0724"},
{"city":"Ostad","cityF":"استاد","lat":"32.7411","lon":"59.13"},
{"city":"Parand","cityF":"پرند","lat":"28.7417","lon":"56.5303"},
{"city":"Pardis","cityF":"پردیس","lat":"30.2591","lon":"48.451"},
{"city":"Park","cityF":"پارک","lat":"25.4954","lon":"60.5626"},
{"city":"Park","cityF":"پارک","lat":"31.8647","lon":"55.8164"},
{"city":"Parnak","cityF":"چرنک","lat":"39.2692","lon":"45.0306"},
{"city":"Pars","cityF":"پارس","lat":"35.7355","lon":"51.5291"},
{"city":"Parsa","cityF":"پارسا","lat":"36.6056","lon":"53.9597"},
{"city":"Parsabad","cityF":"پارس آباد","lat":"39.6482","lon":"47.9174"},
{"city":"Parsian","cityF":"پارسیان","lat":"27.2918","lon":"56.1532"},
{"city":"Parsian","cityF":"پارسیان","lat":"36.1431","lon":"49.9333"},
{"city":"Parsiyan","cityF":"پارسیان","lat":"36.1594","lon":"49.9333"},
{"city":"Parvaz","cityF":"پرواز","lat":"29.0726","lon":"51.4224"},
{"city":"Pasargad","cityF":"پاسارگاد","lat":"30.2019","lon":"53.18"},
{"city":"Payam","cityF":"پیام","lat":"38.3557","lon":"45.8129"},
{"city":"Payam","cityF":"پیام","lat":"38.3592","lon":"45.8161"},
{"city":"Peik","cityF":"پیک","lat":"35.3382","lon":"50.7489"},
{"city":"Peyk","cityF":"پیک","lat":"37.105","lon":"47.1272"},
{"city":"Peyvand","cityF":"پیوند","lat":"35.5961","lon":"50.9367"},
{"city":"Piranshahr","cityF":"پیرانشهر","lat":"36.701","lon":"45.1413"},
{"city":"Pirooz","cityF":"پیروز","lat":"30.3333","lon":"48.2667"},
{"city":"Pishgaman","cityF":"پیشگامان","lat":"37.2683","lon":"48.4419"},
{"city":"Piyam","cityF":"پیام","lat":"38.3557","lon":"45.8129"},
{"city":"Poldasht","cityF":"پلدشت","lat":"39.348","lon":"45.071"},
{"city":"Post","cityF":"پست","lat":"37.7333","lon":"44.8333"},
{"city":"Puyan","cityF":"پویان","lat":"34.7","lon":"47.3"},
{"city":"Qasem","cityF":"قاسم","lat":"32.6167","lon":"48.2833"},
{"city":"Qazvin","cityF":"قزوین","lat":"36.2477","lon":"50.006"},
{"city":"Qazvin","cityF":"قزوین","lat":"36.2622","lon":"50.0169"},
{"city":"Qeshm","cityF":"قشم","lat":"26.9581","lon":"56.2719"},
{"city":"Qods","cityF":"قدس","lat":"32.4016","lon":"48.14"},
{"city":"Qom","cityF":"قم","lat":"34.6401","lon":"50.8764"},
{"city":"Qom","cityF":"قم","lat":"34.6453","lon":"50.8808"},
{"city":"Quchan","cityF":"قوچان","lat":"37.1069","lon":"58.5097"},
{"city":"Rabor","cityF":"رابر","lat":"29.2897","lon":"56.9089"},
{"city":"Rafi","cityF":"رفی","lat":"36.6167","lon":"50.4333"},
{"city":"Rafsanjan","cityF":"رفسنجان","lat":"30.4067","lon":"55.9939"},
{"city":"Rahbaran","cityF":"رهبران","lat":"27.7297","lon":"57.265"},
{"city":"Rahimi","cityF":"رحیمی","lat":"31.4845","lon":"48.3579"},
{"city":"Rakhsh","cityF":"پخش","lat":"35.7833","lon":"52.3"},
{"city":"Ramezani","cityF":"رمضانی","lat":"31.0167","lon":"56.2"},
{"city":"Ramhormoz","cityF":"رامهرمز","lat":"31.2783","lon":"49.6064"},
{"city":"Ramian","cityF":"رامیان","lat":"37.0194","lon":"55.1447"},
{"city":"Ramin","cityF":"رامین","lat":"35.577","lon":"51.061"},
{"city":"Ramin","cityF":"رامین","lat":"36.5539","lon":"48.5586"},
{"city":"Ramsar","cityF":"رامسر","lat":"36.9003","lon":"50.6825"},
{"city":"Rasa","cityF":"رسا","lat":"30.5158","lon":"52.5183"},
{"city":"Rasan","cityF":"رسان","lat":"35.1667","lon":"57.25"},
{"city":"Rashid","cityF":"رشید","lat":"33.55","lon":"47.7333"},
{"city":"Rashidi","cityF":"رشیدی","lat":"33.5547","lon":"49.6389"},
{"city":"Rashidi","cityF":"رشیدی","lat":"34.309","lon":"47.0713"},
{"city":"Rasht","cityF":"رشت","lat":"37.2794","lon":"49.5858"},
{"city":"Ravand","cityF":"راوند","lat":"34.0194","lon":"51.3444"},
{"city":"Ravand","cityF":"راوند","lat":"38.7973","lon":"44.7935"},
{"city":"Ravansar","cityF":"روانسر","lat":"34.7153","lon":"46.6533"},
{"city":"Razan","cityF":"رزن","lat":"33.2194","lon":"52.9733"},
{"city":"Razan","cityF":"رزن","lat":"36.0333","lon":"52.2333"},
{"city":"Razavi","cityF":"رضوی","lat":"34.2833","lon":"58.4667"},
{"city":"Razi","cityF":"رازی","lat":"38.6279","lon":"48.0941"},
{"city":"Resalat","cityF":"رضا","lat":"37.5167","lon":"56.7667"},
{"city":"Reza","cityF":"رضا","lat":"30.3792","lon":"51.4414"},
{"city":"Reza","cityF":"رضا","lat":"32.062","lon":"49.3949"},
{"city":"Rezvanshahr","cityF":"رضوانشهر","lat":"32.7055","lon":"51.104"},
{"city":"Rizi","cityF":"ریزی","lat":"36.8858","lon":"55.1961"},
{"city":"Roshtkhar","cityF":"رشتخوار","lat":"34.9764","lon":"59.625"},
{"city":"Sabalan","cityF":"سبلان","lat":"38.1736","lon":"46.1253"},
{"city":"Sabalan","cityF":"سبلان","lat":"38.1753","lon":"46.129"},
{"city":"Sabz","cityF":"سبز","lat":"37.4269","lon":"47.8175"},
{"city":"Sabz","cityF":"سبز","lat":"37.4315","lon":"47.7874"},
{"city":"Sabzevar","cityF":"سبزوار","lat":"36.2144","lon":"57.6797"},
{"city":"Sadegh","cityF":"صادق","lat":"31.0328","lon":"61.4452"},
{"city":"Sadi","cityF":"سعدی","lat":"30.9667","lon":"61.4"},
{"city":"Sadr","cityF":"صدر","lat":"38.8862","lon":"44.324"},
{"city":"Sadra","cityF":"صدرا","lat":"29.8046","lon":"52.4949"},
{"city":"Safa","cityF":"صفا","lat":"37.4325","lon":"58.2431"},
{"city":"Safashahr","cityF":"صفاشهر","lat":"34.6122","lon":"50.841"},
{"city":"Saghez","cityF":"سقز","lat":"36.2463","lon":"46.2665"},
{"city":"Sahlan","cityF":"سهلان","lat":"38.1753","lon":"46.129"},
{"city":"Sahlan","cityF":"سهلان","lat":"38.2333","lon":"46.0667"},
{"city":"Sahneh","cityF":"صحنه","lat":"34.4813","lon":"47.6908"},
{"city":"Sakhteman","cityF":"ساختمان","lat":"31.1296","lon":"61.4812"},
{"city":"Sakhteman","cityF":"ساختمان","lat":"36.6167","lon":"49.2667"},
{"city":"Salafchegan","cityF":"سلفچگان","lat":"34.4792","lon":"50.4567"},
{"city":"Salamat","cityF":"سلامت","lat":"36.2807","lon":"45.8716"},
{"city":"Salar","cityF":"سالار","lat":"31.4167","lon":"56.2667"},
{"city":"Salar","cityF":"سالار","lat":"35.205","lon":"51.5889"},
{"city":"Salari","cityF":"سالاری","lat":"28.8889","lon":"53.075"},
{"city":"Saleh","cityF":"صالح","lat":"35.9528","lon":"46.3249"},
{"city":"Salman","cityF":"سلمان","lat":"36.6224","lon":"48.4735"},
{"city":"Salmas","cityF":"سلماس","lat":"38.1973","lon":"44.7653"},
{"city":"Salmas","cityF":"سلماس","lat":"38.1975","lon":"44.7681"},
{"city":"Saman","cityF":"سامان","lat":"32.4514","lon":"50.9117"},
{"city":"Saman","cityF":"سامان","lat":"35.2585","lon":"49.5764"},
{"city":"Samangan","cityF":"سمنگان","lat":"34.4518","lon":"47.5553"},
{"city":"Samangan","cityF":"سمنگان","lat":"34.8417","lon":"60.4578"},
{"city":"Samen","cityF":"ثامن","lat":"34.1989","lon":"48.7044"},
{"city":"Sanabad","cityF":"سناباد","lat":"32.9525","lon":"52.5947"},
{"city":"Sanandaj","cityF":"سنندج","lat":"35.3144","lon":"46.9923"},
{"city":"Sangan","cityF":"سنگان","lat":"35.8618","lon":"51.2408"},
{"city":"Saqqez","cityF":"سقز","lat":"36.2463","lon":"46.2665"},
{"city":"Sara","cityF":"سارا","lat":"36.3756","lon":"46.2147"},
{"city":"Sara","cityF":"سارا","lat":"36.4","lon":"45.2"},
{"city":"Sarab","cityF":"سراب","lat":"37.9264","lon":"47.5481"},
{"city":"Sarab","cityF":"سراب","lat":"37.9408","lon":"47.5367"},
{"city":"Sarakhs","cityF":"سرخس","lat":"36.5347","lon":"61.1611"},
{"city":"Saran","cityF":"سران","lat":"37.8417","lon":"46.6857"},
{"city":"Saravan","cityF":"سراوان","lat":"29.0679","lon":"51.4454"},
{"city":"Sard","cityF":"سرد","lat":"32.9834","lon":"48.9248"},
{"city":"Sardaran","cityF":"سرداران","lat":"27.1167","lon":"61.6833"},
{"city":"Sardasht","cityF":"سردشت","lat":"30.7317","lon":"52.6894"},
{"city":"Sardasht","cityF":"سردشت","lat":"35.0581","lon":"46.9146"},
{"city":"Sari","cityF":"ساری","lat":"36.5678","lon":"53.0586"},
{"city":"Sarv","cityF":"سرو","lat":"36.6163","lon":"45.5116"},
{"city":"Sarvabad","cityF":"سروآباد","lat":"35.3126","lon":"46.3669"},
{"city":"Sarvestan","cityF":"سروستان","lat":"28.0406","lon":"51.8289"},
{"city":"Saveh","cityF":"ساوه","lat":"35.0213","lon":"50.3566"},
{"city":"Sayeh","cityF":"سایه","lat":"30.1761","lon":"54.2922"},
{"city":"Sazan","cityF":"سزن","lat":"35.9225","lon":"48.5661"},
{"city":"Sedeh","cityF":"سده","lat":"29.4424","lon":"51.2465"},
{"city":"Semirom","cityF":"سمیرم","lat":"31.4167","lon":"51.5667"},
{"city":"Semnan","cityF":"سمنان","lat":"35.5753","lon":"53.3942"},
{"city":"Send","cityF":"سند","lat":"37.2389","lon":"49.3389"},
{"city":"Sepah","cityF":"سپه","lat":"33.9037","lon":"46.0696"},
{"city":"Sepahan","cityF":"سپاهان","lat":"35.6667","lon":"51.1667"},
{"city":"Sepidan","cityF":"سپیدان","lat":"29.972","lon":"52.4012"},
{"city":"Sepidar","cityF":"سپیدار","lat":"30.5989","lon":"51.3667"},
{"city":"Sepidar","cityF":"سپیدار","lat":"35.3485","lon":"46.3483"},
{"city":"Shabestar","cityF":"شبستر","lat":"38.1804","lon":"45.7028"},
{"city":"Shabestar","cityF":"شبستر","lat":"38.1839","lon":"45.6989"},
{"city":"Shadegan","cityF":"شادگان","lat":"30.6497","lon":"48.6647"},
{"city":"Shafa","cityF":"شفا","lat":"36.5408","lon":"59.4325"},
{"city":"Shaft","cityF":"شفت","lat":"29.0706","lon":"50.8773"},
{"city":"Shahab","cityF":"شهاب","lat":"30.6833","lon":"48.7333"},
{"city":"Shahed","cityF":"شاهد","lat":"28.5928","lon":"52.2297"},
{"city":"Shahid","cityF":"شهید","lat":"28.5928","lon":"52.2297"},
{"city":"Shahid Bahonar","cityF":"شهید باهنر","lat":"29.6967","lon":"52.4612"},
{"city":"Shahid Chamran","cityF":"شهید چمران","lat":"31.1667","lon":"49.6333"},
{"city":"Shahid Chamran","cityF":"شهید چمران","lat":"33.3507","lon":"47.9301"},
{"city":"Shahid Madani","cityF":"شهید مدنی","lat":"33.1559","lon":"47.392"},
{"city":"Shahin","cityF":"شاهین","lat":"35.39","lon":"46.5353"},
{"city":"Shahin Shahr","cityF":"شاهین شهر","lat":"32.8667","lon":"51.5667"},
{"city":"Shahini","cityF":"شاهینی","lat":"34.9267","lon":"46.789"},
{"city":"Shahmirzad","cityF":"شهمیرزاد","lat":"35.7675","lon":"53.325"},
{"city":"Shahr","cityF":"شهر","lat":"36.2333","lon":"52.8333"},
{"city":"Shahrak","cityF":"شهرک","lat":"36.4333","lon":"48.0833"},
{"city":"Shahrak","cityF":"شهرک","lat":"39.1185","lon":"45.3048"},
{"city":"Shahran","cityF":"شهران","lat":"35.7593","lon":"51.2929"},
{"city":"Shahre","cityF":"شهره","lat":"34.3133","lon":"45.9069"},
{"city":"Shahreza","cityF":"شهرضا","lat":"32.0089","lon":"51.8668"},
{"city":"Shahriar","cityF":"شهریار","lat":"31.3481","lon":"51.2244"},
{"city":"Shahriar","cityF":"شهریار","lat":"35.4846","lon":"51.0829"},
{"city":"Shahrivar","cityF":"شهریور","lat":"38.3305","lon":"48.1956"},
{"city":"Shahriyar","cityF":"شهریار","lat":"35.6596","lon":"51.0593"},
{"city":"Shahriyar","cityF":"شهریار","lat":"35.6597","lon":"51.0594"},
{"city":"Shahrood","cityF":"شاهرود","lat":"28.0328","lon":"56.3539"},
{"city":"Shahrud","cityF":"شاهرود","lat":"36.4167","lon":"55.0167"},
{"city":"Shahryar","cityF":"شهریار","lat":"31.3481","lon":"51.2244"},
{"city":"Shahryar","cityF":"شهریار","lat":"35.4846","lon":"51.0829"},
{"city":"Shahsavar","cityF":"شهسوار","lat":"38.3062","lon":"46.8059"},
{"city":"Shahsavar","cityF":"شهسوار","lat":"39.1667","lon":"44.4667"},
{"city":"Shakib","cityF":"شکیب","lat":"34.5833","lon":"47.4833"},
{"city":"Shalamzar","cityF":"شلمزار","lat":"32.0439","lon":"50.8139"},
{"city":"Shamekh","cityF":"شامخ","lat":"36.1492","lon":"58.7286"},
{"city":"Shams","cityF":"شمس","lat":"32.99","lon":"58.7844"},
{"city":"Shand","cityF":"شند","lat":"33.5867","lon":"59.5836"},
{"city":"Sharif","cityF":"شریف","lat":"31.711","lon":"49.1193"},
{"city":"Sharif","cityF":"شریف","lat":"34.0675","lon":"48.0786"},
{"city":"Sharqi","cityF":"شرقی","lat":"28.9333","lon":"53.2667"},
{"city":"Shasta","cityF":"شستا","lat":"36.85","lon":"50.7333"},
{"city":"Shayegan","cityF":"شایگان","lat":"34.6856","lon":"46.4328"},
{"city":"Shayegan","cityF":"شایگان","lat":"36.4336","lon":"58.3756"},
{"city":"Shazand","cityF":"شازند","lat":"33.9356","lon":"49.4083"},
{"city":"Sheikh","cityF":"شیخ","lat":"30.39","lon":"55.9681"},
{"city":"Shekari","cityF":"شکری","lat":"37.4044","lon":"48.8731"},
{"city":"Sheverin","cityF":"شورین","lat":"34.7992","lon":"48.5756"},
{"city":"Sheykh","cityF":"شیخ","lat":"36.1971","lon":"45.4595"},
{"city":"Shimbar","cityF":"شیمبار","lat":"32.65","lon":"49.6"},
{"city":"Shir","cityF":"شیر","lat":"36.6833","lon":"52.4833"},
{"city":"Shiraz","cityF":"شیراز","lat":"29.6036","lon":"52.5388"},
{"city":"Shirvan","cityF":"شیروان","lat":"37.4033","lon":"57.9286"},
{"city":"Shisheh","cityF":"شیشه","lat":"33.8333","lon":"48.7667"},
{"city":"Shohada","cityF":"شهدا","lat":"30.1911","lon":"52.0225"},
{"city":"Shohada","cityF":"شهدا","lat":"33.0284","lon":"47.7628"},
{"city":"Shoosh","cityF":"شوش","lat":"32.1942","lon":"48.2436"},
{"city":"Shooshtar","cityF":"شوشتر","lat":"32.0455","lon":"48.8567"},
{"city":"Shot","cityF":"شوت","lat":"39.2192","lon":"44.77"},
{"city":"Shrifabad","cityF":"شریف آباد","lat":"35.7518","lon":"47.642"},
{"city":"Side","cityF":"ساید","lat":"37.2208","lon":"49.7611"},
{"city":"Silk","cityF":"سیلک","lat":"32.9667","lon":"58.6833"},
{"city":"Siman","cityF":"سیمان","lat":"35.0562","lon":"46.0221"},
{"city":"Simorgh","cityF":"سیمرغ","lat":"32.0597","lon":"59.5231"},
{"city":"Sina","cityF":"سینا","lat":"28.4525","lon":"51.6042"},
{"city":"Sirjan","cityF":"سیرجان","lat":"29.4514","lon":"55.6717"},
{"city":"Sisakht","cityF":"سیسخت","lat":"30.8658","lon":"51.4567"},
{"city":"Sistan","cityF":"سیستان","lat":"28.5167","lon":"53.2833"},
{"city":"Sobhan","cityF":"سبحان","lat":"36.0467","lon":"54.2361"},
{"city":"Soofian","cityF":"سوفیان","lat":"38.2636","lon":"45.9969"},
{"city":"Soola","cityF":"سولا","lat":"38.3857","lon":"48.4818"},
{"city":"Soro","cityF":"سورو","lat":"27.1702","lon":"56.2241"},
{"city":"Tabas","cityF":"طبس","lat":"33.5883","lon":"56.9225"},
{"city":"Tabriz","cityF":"تبریز","lat":"38.0747","lon":"46.2472"},
{"city":"Tabriz","cityF":"تبریز","lat":"38.08","lon":"46.2919"},
{"city":"Tafresh","cityF":"تفرش","lat":"34.6919","lon":"50.025"},
{"city":"Taft","cityF":"تفت","lat":"31.7475","lon":"54.2042"},
{"city":"Taha","cityF":"طاها","lat":"30.2833","lon":"48.4"},
{"city":"Takab","cityF":"تکاب","lat":"36.4009","lon":"47.1133"},
{"city":"Takab","cityF":"تکاب","lat":"36.4056","lon":"47.1183"},
{"city":"Takestan","cityF":"تاکستان","lat":"36.0625","lon":"49.6989"},
{"city":"Takestan","cityF":"تاکستان","lat":"36.0696","lon":"49.6959"},
{"city":"Takhti","cityF":"تختی","lat":"26.2464","lon":"58.9511"},
{"city":"Talar","cityF":"تالار","lat":"27.0517","lon":"57.0644"},
{"city":"Talar","cityF":"تالار","lat":"37.16","lon":"47.0056"},
{"city":"Talesh","cityF":"تالش","lat":"37.7975","lon":"48.8989"},
{"city":"Tamin","cityF":"تمین","lat":"28.6897","lon":"61.1281"},
{"city":"Tamishan","cityF":"تمیشان","lat":"36.5667","lon":"52.05"},
{"city":"Taneh","cityF":"تنه","lat":"36.2167","lon":"51.6"},
{"city":"Tangestan","cityF":"تنگستان","lat":"32.7533","lon":"52.8531"},
{"city":"Tappeh","cityF":"تپه","lat":"38.4105","lon":"48.3671"},
{"city":"Tarasht","cityF":"طرشت","lat":"35.7081","lon":"51.3456"},
{"city":"Taraz","cityF":"تراز","lat":"35.2728","lon":"58.1814"},
{"city":"Taybad","cityF":"تایباد","lat":"34.74","lon":"60.7756"},
{"city":"Teheran","cityF":"تهران","lat":"35.705","lon":"51.4216"},
{"city":"Tehran","cityF":"تهران","lat":"35.6719","lon":"51.4244"},
{"city":"Tina","cityF":"تینا","lat":"32.4333","lon":"49.4667"},
{"city":"Tiran","cityF":"تیران","lat":"36.0914","lon":"52.3922"},
{"city":"Tonekabon","cityF":"تنکابن","lat":"36.8086","lon":"50.8819"},
{"city":"Torkan","cityF":"ترکان","lat":"29.5625","lon":"52.6278"},
{"city":"Torshiz","cityF":"ترشیز","lat":"35.2364","lon":"58.4819"},
{"city":"Towchal","cityF":"توچال","lat":"35.5737","lon":"51.6995"},
{"city":"Towchal","cityF":"توچال","lat":"35.5767","lon":"51.7128"},
{"city":"Urmia","cityF":"اورمیه","lat":"37.555","lon":"45.1028"},
{"city":"Urmia","cityF":"اورمیه","lat":"37.5553","lon":"45.0724"},
{"city":"Vahdat","cityF":"وحدت","lat":"31.0344","lon":"50.4636"},
{"city":"Vahed","cityF":"واحد","lat":"34.0425","lon":"50.9572"},
{"city":"Vahid","cityF":"وحید","lat":"31.4236","lon":"49.1116"},
{"city":"Vakil","cityF":"وکیل","lat":"39.1839","lon":"44.22"},
{"city":"Vala","cityF":"والا","lat":"36.0167","lon":"52.7667"},
{"city":"Vali","cityF":"ولی","lat":"38.3333","lon":"46.9"},
{"city":"Vali","cityF":"ولی","lat":"38.3358","lon":"46.8914"},
{"city":"Vana","cityF":"وانا","lat":"35.9264","lon":"52.2711"},
{"city":"Vanak","cityF":"ونک","lat":"25.5381","lon":"58.8717"},
{"city":"Vanda","cityF":"وندا","lat":"29.7833","lon":"51.55"},
{"city":"Varagh","cityF":"ورق","lat":"35.5114","lon":"49.3761"},
{"city":"Varamin","cityF":"ورامین","lat":"35.3253","lon":"51.6456"},
{"city":"Varzaneh","cityF":"ورزانه","lat":"32.4189","lon":"52.6486"},
{"city":"Velayat","cityF":"ولایت","lat":"28.0553","lon":"52.0542"},
{"city":"Velenjak","cityF":"ولنجک","lat":"35.8147","lon":"51.4133"},
{"city":"Yadak","cityF":"یدک","lat":"37.1281","lon":"58.8922"},
{"city":"Yadegar","cityF":"یادگار","lat":"30.8976","lon":"61.723"},
{"city":"Yadegar","cityF":"یادگار","lat":"37.2619","lon":"58.5814"},
{"city":"Yaran","cityF":"یاران","lat":"34.5167","lon":"45.9667"},
{"city":"Yasooj","cityF":"یاسوج","lat":"30.6517","lon":"51.615"},
{"city":"Yasuj","cityF":"یاسوج","lat":"30.6517","lon":"51.615"},
{"city":"Yazd","cityF":"یزد","lat":"31.8972","lon":"54.3675"},
{"city":"Zabol","cityF":"زابل","lat":"31.0287","lon":"61.5012"},
{"city":"Zahedan","cityF":"زاهدان","lat":"28.7449","lon":"53.8033"},
{"city":"Zahedan","cityF":"زاهدان","lat":"29.4978","lon":"60.8728"},
{"city":"Zahra","cityF":"زهرا","lat":"39.0472","lon":"48.292"},
{"city":"Zaman","cityF":"زمان","lat":"33.8441","lon":"46.4707"},
{"city":"Zamin","cityF":"زمین","lat":"36.5167","lon":"49.5"},
{"city":"Zand","cityF":"زند","lat":"37.5934","lon":"48.156"},
{"city":"Zangan","cityF":"زنگان","lat":"36.6206","lon":"49.3375"},
{"city":"Zangan","cityF":"زنگان","lat":"39.5798","lon":"44.8853"},
{"city":"Zangiabad","cityF":"زنگی آباد","lat":"29.9745","lon":"52.8563"},
{"city":"Zanjan","cityF":"زنجان","lat":"36.6644","lon":"48.4856"},
{"city":"Zanjan","cityF":"زنجان","lat":"36.6736","lon":"48.4787"},
{"city":"Zarand","cityF":"زرند","lat":"30.8108","lon":"56.5672"},
{"city":"Zargan","cityF":"زرگان","lat":"29.7741","lon":"52.7235"},
{"city":"Zarin","cityF":"زرین","lat":"35.7667","lon":"54.15"},
{"city":"Zarreh","cityF":"زره","lat":"30.055","lon":"55.1017"},
{"city":"Zarreh","cityF":"زره","lat":"35.0692","lon":"49.1944"},
{"city":"Zarrin","cityF":"زرین","lat":"35.7667","lon":"54.15"},
{"city":"Zarrin","cityF":"زرین","lat":"38.4088","lon":"47.1131"},
{"city":"Zarrin Shahr","cityF":"زرین شهر","lat":"32.3897","lon":"51.3766"},
{"city":"Zarrin Shahr","cityF":"زرین شهر","lat":"32.3967","lon":"51.3883"},
{"city":"Zarrineh","cityF":"زرینه","lat":"33.9297","lon":"46.1824"},
{"city":"Zarrineh","cityF":"زرینه","lat":"36.7167","lon":"50.2167"},
{"city":"Zharf","cityF":"ژرف","lat":"35.3697","lon":"59.8914"},
{"city":"Ziarat","cityF":"زیارت","lat":"26.6503","lon":"57.0805"},
{"city":"Ziarat","cityF":"زیارت","lat":"36.3667","lon":"47.9667"},
{"city":"Zirab","cityF":"زیراب","lat":"28.4806","lon":"54.4828"},
{"city":"Ziyarat","cityF":"زیارت","lat":"28.1664","lon":"51.3712"},
{"city":"Abdulla","cityF":"عبد الله","lat":"30.9167","lon":"46.4167"},
{"city":"Abdullah","cityF":"عبد الله","lat":"30.9167","lon":"46.4167"},
{"city":"Al Karradah","cityF":"الكرادة","lat":"33.3022","lon":"44.4383"},
{"city":"Al Kut","cityF":"الكوت","lat":"32.4975","lon":"45.8292"},
{"city":"Amara","cityF":"العمارة","lat":"31.8453","lon":"47.1753"},
{"city":"An Najaf","cityF":"النجف","lat":"31.9961","lon":"44.3147"},
{"city":"Aran","cityF":"أران","lat":"35.1583","lon":"43.4439"},
{"city":"Arbil","cityF":"اربيل","lat":"36.19","lon":"44.0089"},
{"city":"Babil","cityF":"بابل","lat":"32.5411","lon":"44.4297"},
{"city":"Bagdad","cityF":"بغداد","lat":"33.3386","lon":"44.3939"},
{"city":"Baghdad","cityF":"بغداد","lat":"33.3386","lon":"44.3939"},
{"city":"Basra","cityF":"البصرة","lat":"30.4942","lon":"47.8192"},
{"city":"Basrah","cityF":"البصرة","lat":"36.0994","lon":"44.8244"},
{"city":"Bayji","cityF":"بيجي","lat":"34.925","lon":"43.4875"},
{"city":"Diwaniya","cityF":"الديوانية","lat":"33.0014","lon":"44.5822"},
{"city":"Diwaniyah","cityF":"الديوانية","lat":"33.0014","lon":"44.5822"},
{"city":"Dohuk","cityF":"دهوك","lat":"36.8658","lon":"42.9997"},
{"city":"Duhok","cityF":"دهوك","lat":"37.1042","lon":"43.8308"},
{"city":"Dukan","cityF":"دوكان","lat":"35.25","lon":"45.55"},
{"city":"Erbil","cityF":"أربيل","lat":"36.19","lon":"44.0089"},
{"city":"Goran","cityF":"غوران","lat":"35.5736","lon":"44.6089"},
{"city":"Hilla","cityF":"الحلة","lat":"32.4794","lon":"44.4328"},
{"city":"Irbil","cityF":"اربيل","lat":"36.19","lon":"44.0089"},
{"city":"Karrada","cityF":"الكرادة","lat":"33.3022","lon":"44.4383"},
{"city":"Kerbala","cityF":"كربلاء","lat":"32.5978","lon":"44.0161"},
{"city":"Khalid","cityF":"خالد","lat":"36.1589","lon":"43.5942"},
{"city":"Khanzad","cityF":"خانزاد","lat":"36.3372","lon":"44.1619"},
{"city":"Kirkuk","cityF":"كركوك","lat":"35.4681","lon":"44.3922"},
{"city":"Koya","cityF":"كويه","lat":"36.1244","lon":"45.1778"},
{"city":"Kut","cityF":"الكوت","lat":"32.4975","lon":"45.8292"},
{"city":"Kuwait","cityF":"الكويت","lat":"34.2167","lon":"43.8667"},
{"city":"Mansur","cityF":"منصور","lat":"31.4333","lon":"45.3667"},
{"city":"Mosul","cityF":"الموصل","lat":"36.335","lon":"43.1189"},
{"city":"Najaf","cityF":"النجف","lat":"31.9961","lon":"44.3147"},
{"city":"Nasiriyah","cityF":"الناصرية","lat":"31.0542","lon":"46.2594"},
{"city":"Ramadi","cityF":"الرمادي","lat":"33.4239","lon":"43.3025"},
{"city":"Ranya","cityF":"رانية","lat":"36.2556","lon":"44.8853"},
{"city":"Riyadh","cityF":"الرياض","lat":"35.3","lon":"43.9167"},
{"city":"Saida","cityF":"صيدا","lat":"34.6742","lon":"45.1869"},
{"city":"Salim","cityF":"سالم","lat":"33.2667","lon":"44.4"},
{"city":"Samawa","cityF":"السماوة","lat":"31.3094","lon":"45.2803"},
{"city":"Sara","cityF":"سارة","lat":"37.1975","lon":"44.2128"},
{"city":"Sidra","cityF":"السدرة","lat":"30.6333","lon":"47.0167"},
{"city":"Sulaimani","cityF":"السليمانية","lat":"34.0333","lon":"44.8167"},
{"city":"Sulaimania","cityF":"السليمانية","lat":"35.5617","lon":"45.4408"},
{"city":"Sulaimaniya","cityF":"السليمانية","lat":"34.1497","lon":"42.3819"},
{"city":"Sulaymani","cityF":"سليمان","lat":"34.0333","lon":"44.8167"},
{"city":"Sulaymaniyah","cityF":"سليمان","lat":"34.1497","lon":"42.3819"},
{"city":"Thamir","cityF":"ثامر","lat":"31.3667","lon":"46.1167"},
{"city":"Tikrit","cityF":"تكريت","lat":"34.5967","lon":"43.6769"},
{"city":"Umm Qasr","cityF":"أم قصر","lat":"30.0342","lon":"47.9294"},
{"city":"Washash","cityF":"الوشاش","lat":"33.3333","lon":"44.35"},
{"city":"Zakho","cityF":"زاخو","lat":"37.1442","lon":"42.6872"},
{"city":"ali Al Ahmad","cityF":"أحمد","lat":"33.0667","lon":"44.05"}]